hikvisionapi/__init__.py
hikvisionapi/hikvisionapi.py
tests/__init__.py
tests/test_hikvisionapi.py
hikvisionapi-0.3.2.dist-info/LICENSE.txt
hikvisionapi-0.3.2.dist-info/METADATA
hikvisionapi-0.3.2.dist-info/WHEEL
hikvisionapi-0.3.2.dist-info/top_level.txt
hikvisionapi-0.3.2.dist-info/RECORD
