Metadata-Version: 2.1
Name: hikvisionapi
Version: 0.3.2
Summary: The client for HIKVISION cameras, DVR
Home-page: https://github.com/MissiaL/hikvision-client
Download-URL: https://github.com/MissiaL/hikvision-client/tarball/0.3.2
Author: Petr Alekseev
Author-email: petrmissial@gmail.com
License: UNKNOWN
Keywords: api,hikvision,hikvision-client
Platform: UNKNOWN
Requires-Python: >3.5
License-File: LICENSE.txt
